cookiecutter_pypackage_test/__init__.py
cookiecutter_pypackage_test/__main__.py
cookiecutter_pypackage_test/cli.py
cookiecutter_pypackage_test/core.py
cookiecutter_pypackage_test-1.0.0.dist-info/LICENSE
cookiecutter_pypackage_test-1.0.0.dist-info/METADATA
cookiecutter_pypackage_test-1.0.0.dist-info/WHEEL
cookiecutter_pypackage_test-1.0.0.dist-info/entry_points.txt
cookiecutter_pypackage_test-1.0.0.dist-info/top_level.txt
cookiecutter_pypackage_test-1.0.0.dist-info/RECORD
