Metadata-Version: 2.1
Name: cookiecutter-pypackage-test
Version: 1.0.0
Summary: A test package for our pypackage cookiecutter.
Home-page: https://github.com/hypothesis/cookiecutter-pypackage-test
Project-URL: Bug Tracker, https://github.com/hypothesis/cookiecutter-pypackage-test/issues
Project-URL: Changelog, https://github.com/hypothesis/cookiecutter-pypackage-test/releases
Classifier: Programming Language :: Python :: 3
Classifier: License :: OSI Approved :: BSD License
Classifier: Intended Audience :: Developers
Requires-Python: >=3.7
License-File: LICENSE
Requires-Dist: sqlalchemy
Requires-Dist: psycopg2
Requires-Dist: importlib-metadata ; python_version < "3.8."
